{
  "folder": "hBmSEMgN7c4ptMT7",
  "name": "A protective amulet",
  "type": "equipment",
  "img": "modules/pbta-rhapsodyofblood/assets/icons/armaments/amulet.svg",
  "system": {
    "name": "",
    "description": "<p>destroy to avoid marking contamination or to loose 1 contamination</p>",
    "uses": 0,
    "playbook": "",
    "quantity": 1,
    "weight": 0,
    "tags": "",
    "tagsString": "",
    "itemType": null,
    "equipmentType": "gear"
  },
  "effects": [],
  "ownership": {
    "default": 0,
    "zyc9SZg8VUZgkrt7": 3
  },
  "flags": {
    "core": {}
  },
  "_stats": {
    "systemId": "pbta",
    "systemVersion": "0.9.0.beta-2",
    "coreVersion": "11.315",
    "createdTime": 1698557609451,
    "modifiedTime": 1707679574431,
    "lastModifiedBy": "akEtZ5rzk6nEDcRX"
  },
  "_id": "PELqfJW4a6DFxj4T",
  "sort": 1900000,
  "_key": "!items!PELqfJW4a6DFxj4T"
}
