{
  "folder": "hBmSEMgN7c4ptMT7",
  "name": "A shield",
  "type": "equipment",
  "img": "modules/pbta-rhapsodyofblood/assets/icons/armaments/shield.svg",
  "system": {
    "name": "",
    "description": "<p>Advantage on <strong><em>Confront</em>, </strong>Disadvantage on <em><strong>Dodge</strong></em></p>",
    "uses": 0,
    "playbook": "",
    "quantity": 1,
    "weight": 0,
    "tags": "",
    "tagsString": "",
    "itemType": null,
    "equipmentType": "gear",
    "actorType": "character"
  },
  "effects": [],
  "ownership": {
    "default": 0,
    "zyc9SZg8VUZgkrt7": 3
  },
  "flags": {
    "core": {}
  },
  "_stats": {
    "systemId": "pbta",
    "systemVersion": "1.0.17",
    "coreVersion": "12.327",
    "createdTime": 1698557189143,
    "modifiedTime": 1719435403500,
    "lastModifiedBy": "idJMLpAq6SWnmenZ",
    "compendiumSource": null,
    "duplicateSource": null
  },
  "_id": "96fCnM3u1ZbTaK0f",
  "sort": 2000000,
  "_key": "!items!96fCnM3u1ZbTaK0f"
}
